core/__init__.py
core/config.py
core/init.py
core/logging_config.py
core/metrics.py
core/orchestrator.py
core/request_handler.py
core/scan_model.py
core/schemas.py
core/utils.py
reporting/__init__.py
reporting/export_formats.py
reporting/export_validator.py
reporting/init.py
reporting/report_generator.py
reporting/templates/report.html
vscanx-2.1.0.dist-info/licenses/LICENCE
vscanx-2.1.0.dist-info/METADATA
vscanx-2.1.0.dist-info/WHEEL
vscanx-2.1.0.dist-info/entry_points.txt
vscanx-2.1.0.dist-info/top_level.txt
vscanx-2.1.0.dist-info/RECORD
