Metadata-Version: 2.4
Name: vscanx
Version: 2.1.0
Summary: Ethical Vulnerability Scanner - Modular Security Testing Framework
Home-page: https://github.com/yourusername/vscanx
Author: VScanX Contributors
Author-email: VScanX Contributors <security@example.com>
License: MIT
Project-URL: Homepage, https://github.com/yourusername/vscanx
Project-URL: Documentation, https://github.com/yourusername/vscanx/blob/main/README.md
Project-URL: Repository, https://github.com/yourusername/vscanx
Project-URL: Issues, https://github.com/yourusername/vscanx/issues
Keywords: security,vulnerability,scanner,ethical,pentesting
Classifier: Development Status :: 4 - Beta
Classifier: Intended Audience :: Information Technology
Classifier: Topic :: Security
Classifier: Topic :: System :: Networking :: Monitoring
Classifier: License :: OSI Approved :: MIT License
Classifier: Programming Language :: Python :: 3
Classifier: Programming Language :: Python :: 3.8
Classifier: Programming Language :: Python :: 3.9
Classifier: Programming Language :: Python :: 3.10
Classifier: Programming Language :: Python :: 3.11
Classifier: Programming Language :: Python :: 3.12
Classifier: Operating System :: OS Independent
Requires-Python: >=3.8
License-File: LICENCE
Requires-Dist: requests>=2.31.0
Requires-Dist: scapy>=2.5.0
Requires-Dist: jinja2>=3.1.2
Requires-Dist: jsonschema>=4.19.0
Provides-Extra: dev
Requires-Dist: pytest>=7.4.0; extra == "dev"
Requires-Dist: pytest-cov>=4.1.0; extra == "dev"
Requires-Dist: ruff>=0.1.0; extra == "dev"
Provides-Extra: pdf
Requires-Dist: reportlab>=4.0.0; extra == "pdf"
Dynamic: author
Dynamic: home-page
Dynamic: license-file
Dynamic: requires-python
